pipcryptographylibaryV2/__init__.py
pipcryptographylibaryV2-1.2.0.dist-info/METADATA
pipcryptographylibaryV2-1.2.0.dist-info/WHEEL
pipcryptographylibaryV2-1.2.0.dist-info/top_level.txt
pipcryptographylibaryV2-1.2.0.dist-info/RECORD
