Metadata-Version: 2.1
Name: pipcryptographylibaryV2
Version: 1.2.0
Summary: Crypto Package
Home-page: UNKNOWN
Author: NHJonas
Author-email: nick.faltermeier@gmx.de
License: UNKNOWN
Keywords: python
Platform: UNKNOWN
Classifier: Operating System :: Microsoft :: Windows
